kks/__init__.py
kks/binary.py
kks/cli.py
kks/ejudge.py
kks/ejudge_submit.py
kks/util.py
kks/cmd/__init__.py
kks/cmd/auth.py
kks/cmd/gen.py
kks/cmd/init.py
kks/cmd/lint.py
kks/cmd/open.py
kks/cmd/run.py
kks/cmd/status.py
kks/cmd/submit.py
kks/cmd/sync.py
kks/cmd/test.py
kks/cmd/top.py
kks/cmd/upgrade.py
kokos-1.2.2.dist-info/METADATA
kokos-1.2.2.dist-info/WHEEL
kokos-1.2.2.dist-info/entry_points.txt
kokos-1.2.2.dist-info/top_level.txt
kokos-1.2.2.dist-info/RECORD
