Metadata-Version: 2.1
Name: kokos
Version: 1.2.2
Summary: KoKoS helper tool
Home-page: UNKNOWN
Author: Vyacheslav Boben
Author-email: UNKNOWN
License: UNKNOWN
Platform: UNKNOWN
Requires-Dist: Click
Requires-Dist: requests
Requires-Dist: configparser
Requires-Dist: colorama
Requires-Dist: tqdm
Requires-Dist: beautifulsoup4
